setup.cfg
setup.py
p8dl/__init__.py
p8dl/cli.py
p8dl/downloader.py
p8dl.egg-info/PKG-INFO
p8dl.egg-info/SOURCES.txt
p8dl.egg-info/dependency_links.txt
p8dl.egg-info/entry_points.txt
p8dl.egg-info/requires.txt
p8dl.egg-info/top_level.txt