Metadata-Version: 1.1
Name: p8dl
Version: 0.1
Summary: PICO-8 cartridge downloader
Home-page: https://github.com/franciscod/p8dl
Author: Francisco Demartino
Author-email: demartino.francisco@gmail.com
License: UNKNOWN
Download-URL: https://github.com/franciscod/p8dl/tarball/0.1
Keywords: pico8,pico-8,lexaloffle
Platform: UNKNOWN
